<PAMDataset>
  <Metadata domain="IMAGE_STRUCTURE">
    <MDI key="INTERLEAVE">BAND</MDI>
  </Metadata>
  <Metadata>
    <MDI key="Band_1">Band 1</MDI>
    <MDI key="Band_2">Band 2</MDI>
    <MDI key="Band_3">Band 3</MDI>
    <MDI key="Band_4">Band 4</MDI>
    <MDI key="Band_5">Band 5</MDI>
  </Metadata>
  <Metadata domain="ENVI">
    <MDI key="bands">5</MDI>
    <MDI key="band_names">{Band 1,Band 2,Band 3,Band 4,Band 5}</MDI>
    <MDI key="byte_order">0</MDI>
    <MDI key="coordinate_system_string">{PROJCS["WGS_1984_UTM_Zone_21S",GEOGCS["GCS_WGS_1984",DATUM["D_WGS_1984",SPHEROID["WGS_1984",6378137,298.257223563]],PRIMEM["Greenwich",0],UNIT["Degree",0.017453292519943295]],PROJECTION["Transverse_Mercator"],PARAMETER["latitude_of_origin",0],PARAMETER["central_meridian",-57],PARAMETER["scale_factor",0.9996],PARAMETER["false_easting",500000],PARAMETER["false_northing",10000000],UNIT["Meter",1]]}</MDI>
    <MDI key="data_type">12</MDI>
    <MDI key="description">{C:\Users\geo_beja\Repositories\QGIS_Plugins\SenseCarbonTSViewer\example\Images\re_2012-07-24.bsq}</MDI>
    <MDI key="file_type">ENVI Standard</MDI>
    <MDI key="header_offset">0</MDI>
    <MDI key="interleave">bsq</MDI>
    <MDI key="lines">148</MDI>
    <MDI key="map_info">{UTM, 1, 1, 681139.895559748, 9248218.2820867, 5, 5, 21, South,WGS-84}</MDI>
    <MDI key="samples">432</MDI>
  </Metadata>
  <PAMRasterBand band="1">
    <Description>Band 1</Description>
    <Histograms>
      <HistItem>
        <HistMin>0</HistMin>
        <HistMax>0</HistMax>
        <BucketCount>1</BucketCount>
        <IncludeOutOfRange>0</IncludeOutOfRange>
        <Approximate>0</Approximate>
        <HistCounts>0</HistCounts>
      </HistItem>
    </Histograms>
    <Metadata>
      <MDI key="STATISTICS_MAXIMUM">0</MDI>
      <MDI key="STATISTICS_MEAN">0</MDI>
      <MDI key="STATISTICS_MINIMUM">0</MDI>
      <MDI key="STATISTICS_STDDEV">0</MDI>
    </Metadata>
  </PAMRasterBand>
  <PAMRasterBand band="2">
    <Description>Band 2</Description>
    <Histograms>
      <HistItem>
        <HistMin>0</HistMin>
        <HistMax>0</HistMax>
        <BucketCount>1</BucketCount>
        <IncludeOutOfRange>0</IncludeOutOfRange>
        <Approximate>0</Approximate>
        <HistCounts>0</HistCounts>
      </HistItem>
    </Histograms>
    <Metadata>
      <MDI key="STATISTICS_MAXIMUM">0</MDI>
      <MDI key="STATISTICS_MEAN">0</MDI>
      <MDI key="STATISTICS_MINIMUM">0</MDI>
      <MDI key="STATISTICS_STDDEV">0</MDI>
    </Metadata>
  </PAMRasterBand>
  <PAMRasterBand band="3">
    <Description>Band 3</Description>
    <Histograms>
      <HistItem>
        <HistMin>0</HistMin>
        <HistMax>0</HistMax>
        <BucketCount>1</BucketCount>
        <IncludeOutOfRange>0</IncludeOutOfRange>
        <Approximate>0</Approximate>
        <HistCounts>0</HistCounts>
      </HistItem>
    </Histograms>
    <Metadata>
      <MDI key="STATISTICS_MAXIMUM">0</MDI>
      <MDI key="STATISTICS_MEAN">0</MDI>
      <MDI key="STATISTICS_MINIMUM">0</MDI>
      <MDI key="STATISTICS_STDDEV">0</MDI>
    </Metadata>
  </PAMRasterBand>
  <PAMRasterBand band="4">
    <Description>Band 4</Description>
  </PAMRasterBand>
  <PAMRasterBand band="5">
    <Description>Band 5</Description>
  </PAMRasterBand>
</PAMDataset>
